Metadata-Version: 2.1
Name: asyncosu
Version: 0.0.2
Summary: Async osu! Api Wrapper
Home-page: https://github.com/aticie/async_osu_api
Author: Efehan Atıcı
Author-email: efehanatici@gmail.com
License: UNKNOWN
Project-URL: Bug Tracker, https://github.com/aticie/async_osu_api/issues
Platform: UNKNOWN
Classifier: Programming Language :: Python :: 3
Classifier: License :: OSI Approved :: MIT License
Classifier: Operating System :: OS Independent
Requires-Python: >=3.6
License-File: LICENSE
